folderdiff/__init__.py
folderdiff/__version__.py
folderdiff/cli.py
folderdiff-0.0.2.dist-info/LICENSE
folderdiff-0.0.2.dist-info/METADATA
folderdiff-0.0.2.dist-info/WHEEL
folderdiff-0.0.2.dist-info/entry_points.txt
folderdiff-0.0.2.dist-info/top_level.txt
folderdiff-0.0.2.dist-info/RECORD
